govee/__init__.py
govee/cli.py
govee/client.py
govee/exceptions.py
govee/lan_scan.py
govee/models.py
govee/api/__init__.py
govee/api/cloud/__init__.py
govee/api/cloud/device_control.py
govee/api/cloud/device_diy_scenes.py
govee/api/cloud/device_events.py
govee/api/cloud/device_scenes.py
govee/api/cloud/device_state.py
govee/api/cloud/devices.py
govee/api/lan/__init__.py
govee/api/lan/brightness.py
govee/api/lan/color.py
govee/api/lan/discovery.py
govee/api/lan/power.py
govee/api/lan/status.py
govee/discovery/__init__.py
govee/discovery/sync.py
govee_python-1.0.0.dist-info/licenses/LICENSE
govee_python-1.0.0.dist-info/METADATA
govee_python-1.0.0.dist-info/WHEEL
govee_python-1.0.0.dist-info/entry_points.txt
govee_python-1.0.0.dist-info/top_level.txt
govee_python-1.0.0.dist-info/RECORD
