Metadata-Version: 2.4
Name: govee-python
Version: 1.0.0
Summary: Python library for controlling Govee smart lights via LAN and Cloud APIs
Author-email: Your Name <your.email@example.com>
License: MIT
Project-URL: Homepage, https://github.com/yourusername/govee-python
Project-URL: Documentation, https://github.com/yourusername/govee-python#readme
Project-URL: Repository, https://github.com/yourusername/govee-python
Project-URL: Bug Tracker, https://github.com/yourusername/govee-python/issues
Keywords: govee,smart-lights,iot,home-automation,led
Classifier: Development Status :: 4 - Beta
Classifier: Intended Audience :: Developers
Classifier: License :: OSI Approved :: MIT License
Classifier: Programming Language :: Python :: 3
Classifier: Programming Language :: Python :: 3.8
Classifier: Programming Language :: Python :: 3.9
Classifier: Programming Language :: Python :: 3.10
Classifier: Programming Language :: Python :: 3.11
Classifier: Programming Language :: Python :: 3.12
Classifier: Topic :: Home Automation
Classifier: Topic :: Software Development :: Libraries :: Python Modules
Requires-Python: >=3.8
License-File: LICENSE
Requires-Dist: requests>=2.31.0
Requires-Dist: pyyaml>=6.0
Provides-Extra: dev
Requires-Dist: pytest>=7.4.0; extra == "dev"
Requires-Dist: pytest-cov>=4.1.0; extra == "dev"
Requires-Dist: black>=23.7.0; extra == "dev"
Requires-Dist: ruff>=0.0.280; extra == "dev"
Requires-Dist: mypy>=1.4.0; extra == "dev"
Dynamic: license-file
